[
  {
    "id": 1,
    "name": "Crackshot",
    "image": "./Fortnite/Crackshot.jpg",
    "occupation": "Fry Cook",
    "location": "A Pineapple Under the Sea",
    "userSelected": false,
    "matched": false
  },
  {
    "id": 2,
    "name": "CuddleTeamLeader",
    "image": "./Fortnite/cuddleteamleader.jpg",
    "occupation": "Restaurant Owner",
    "location": "A Giant Anchor",
    "userSelected": false,
    "matched": false
  },
  {
    "id": 3,
    "name": "Default",
    "image": "./Fortnite/Default Skin.jpg",
    "occupation": "Cashier",
    "location": "An Easter Island Head",
    "userSelected": false,
    "matched": false
  },
  {
    "id": 4,
    "name": "Durr Burger",
    "image": "./Fortnite/Durr Burger.jpg",
    "occupation": "Boy Genius",
    "location": "A Secret Laboratory",
    "userSelected": false,
    "matched": false
  },
  {
    "id": 5,
    "name": "John Wick",
    "image": "./Fortnite/John Wick.jpg",
    "occupation": "A Cowardly Dog",
    "location": "Nowhere, Kansas",
    "userSelected": false,
    "matched": false
  },
  {
    "id": 6,
    "name": "Love Ranger",
    "image": "./Fortnite/Love Ranger.jpg",
    "occupation": "Student",
    "location": "Bluffington",
    "userSelected": false,
    "matched": false
  },
  {
    "id": 7,
    "name": "Merry Marauder",
    "image": "./Fortnite/Merry Marauder.jpg",
    "occupation": "Looney Toon",
    "location": "A Rabbit Burrow",
    "userSelected": false,
    "matched": false
  },
  {
    "id": 8,
    "name": "Oblivion",
    "image": "./Fortnite/Oblivion.png",
    "occupation": "Ladies Man",
    "location": "Aron City",
    "userSelected": false,
    "matched": false
  },
  {
    "id": 9,
    "name": "Red Knight",
    "image": "./Fortnite/Red Knight.jpg",
    "occupation": "Adventurer",
    "location": "California",
    "userSelected": false,
    "matched": false
  },
  {
    "id": 10,
    "name": "Skull Trooper",
    "image": "./Fortnite/SkullTrooper.jpg",
    "occupation": "Cashier",
    "location": "O-Town, California",
    "userSelected": false,
    "matched": false
  },
  {
    "id": 11,
    "name": "Valor",
    "image": "./Fortnite/Valor.jpg",
    "occupation": "Superhero",
    "location": "Earth",
    "userSelected": false,
    "matched": false
  },
  {
    "id": 12,
    "name": "Whiplash",
    "image": "./Fortnite/Whiplash.jpg",
    "occupation": "Ahhhh! A Real Monster!",
    "location": "Under a City Dump",
    "userSelected": false,
    "matched": false
  }
]
